fchic/__init__.py
fchic/parser_definition.py
fchic/py.typed
fchic-0.1.1.dist-info/LICENSE
fchic-0.1.1.dist-info/METADATA
fchic-0.1.1.dist-info/WHEEL
fchic-0.1.1.dist-info/top_level.txt
fchic-0.1.1.dist-info/RECORD
