Metadata-Version: 2.1
Name: fchic
Version: 0.1.1
Summary: fchic is a minimal parser for Gaussian 16 formatted checkpoint files.
Home-page: https://github.com/clavigne/fchic
Author: Cyrille Lavigne
Author-email: cyrille.lavigne@mail.utoronto.ca
License: MIT
Keywords: chemistry gaussian16 g16
Platform: UNKNOWN
Classifier: Development Status :: 3 - Alpha
Classifier: Typing :: Typed
Classifier: License :: OSI Approved :: MIT License
Classifier: Programming Language :: Python :: 3.7
Classifier: Programming Language :: Python :: 3.8
Classifier: Programming Language :: Python :: 3.9
Classifier: Intended Audience :: Science/Research
Classifier: Topic :: Scientific/Engineering :: Chemistry
Classifier: Topic :: Scientific/Engineering :: Physics
Requires-Python: >=3.7
License-File: LICENSE
Requires-Dist: pyparsing
Requires-Dist: importlib-metadata (~=1.0) ; python_version < "3.8"
